elegant_json/__init__.py
elegant_json/_json_attribute.py
elegant_json/_json_class.py
elegant_json/core.py
elegant_json-0.1.0.dist-info/LICENSE
elegant_json-0.1.0.dist-info/METADATA
elegant_json-0.1.0.dist-info/WHEEL
elegant_json-0.1.0.dist-info/top_level.txt
elegant_json-0.1.0.dist-info/RECORD
