Metadata-Version: 2.1
Name: elegant-json
Version: 0.1.0
Summary: Deal with JSON in an elegant way
Home-page: UNKNOWN
Author: Hanjin Liu
Author-email: liuhanjin-sc@g.ecc.u-tokyo.ac.jp
License: BSD 3-Clause
Download-URL: https://github.com/hanjinliu/elegant-json
Platform: UNKNOWN
Requires-Python: >=3.8
License-File: LICENSE
